jotbox/__init__.py
jotbox/compat.py
jotbox/exceptions.py
jotbox/json.py
jotbox/py.typed
jotbox/sessions/__init__.py
jotbox/tokens.py
jotbox/types.py
jotbox/util.py
jotbox/whitelist/__init__.py
jotbox/whitelist/base.py
jotbox/whitelist/redis.py
jotbox-0.4.0.dist-info/LICENSE
jotbox-0.4.0.dist-info/METADATA
jotbox-0.4.0.dist-info/WHEEL
jotbox-0.4.0.dist-info/RECORD
